{"_id":"0p54iI8tzj2SB5FBdvQTIwq0VgrOAH6JboSx1it2jBIMkGSE","basic_info":{"calories_value":"35","cooking_type_detail":"烧：烧制菜肴的食材往往需经炸煎后再勾芡汁，使得油脂与淀粉结合，食用时容易在不知不觉中摄入过量油脂导致热量超标，减肥期间需注意控制分量。\n\n        ","food_group_name":"江西菜 ","food_name":"鱼饼","traffic_light_img_href":"http://s2.boohee.cn/house/food_mid/mid_photo_201281615321710496.jpg"},"href":"http://www.boohee.com/shiwu/yubing","material_info":{"major_material_info":["鳜鱼 250克"],"seasoning_info":["精盐 15克","玉米淀粉 30克","味精 3克","香油 5克","菜籽油 50克","猪油(炼) 15克","饮用水 400克"],"supplementary_material_info":["鸡蛋 100克","菠菜 25克","香菇（鲜） 15克"]},"nutrition_info":[{"热量(大卡)":"130.60"},{"碳水化合物(克)":"3.42"},{"脂肪(克)":"9.84"},{"蛋白质(克)":"7.22"},{"纤维素(克)":"0.10"}],"production_method":[" 1. 将净鱼肉用刀剁茸，盛入盆内；","2. 菠菜择洗干净，切段；","3. 香菇去蒂洗净，用冷水涨发，大的一撕两半，待用；","4. 用碗盛清水100毫升，加入淀粉调匀，倒入盛鱼茸的盆内和匀；","5. 和匀的鱼茸再加入细盐10克，从左至右顺一个方向搅打，加入鲜蛋搅打上劲；","6. 锅置中火烧热，加入菜籽油，加热至六成，用左手抓鱼茸，以拇指与食指间挤出，略比肉丸大些，用瓷汤匙蘸水，逐个舀入油锅中炸；","7. 待鱼茸浮于油面时，开始象点油的灯盏一样，中间陷下去，既而逐渐膨胀，像乒乓球浮于油面，待呈淡黄色，翻动时略有响声，即可捞起滤油；","8. 炸好的鱼饼捞出片刻，每个鱼饼即会软落；","9. 将锅放炉火上，加入鲜汤1000毫升，放入鱼饼，烧开10 分钟；","10. 鱼饼里面会饱含汤汁，再加盐10 克、水发香菇、味精、最后放菠菜、大油，起锅盛碗内，淋上香油即可。 "],"relative_foods_info":["鱼饼","蛋卷鲔鱼饼","菌油煎鱼饼","一坊一品 鱼饼"],"source":"薄荷","widget_unit_info":[]}
{"_id":"3ueL49nHfoAvyxCMDjjc6S1jjqJfqKVJu2wXEL8LrY0YVyQI","basic_info":{"calories_value":"10","cooking_type_detail":"炸：食材经油炸后大量吸收油脂，不仅热量大增，严重影响减肥，还会产生致癌物质，不利于健康，因此减肥期间应完全杜绝油炸食物。\n\n        ","food_group_name":"江西菜 ","food_name":"油酥花生米","traffic_light_img_href":"http://s2.boohee.cn/house/upload_food/2008/11/13/user_mid_145649_1226547364.jpg"},"href":"http://www.boohee.com/shiwu/yousuhuashengmi","material_info":{"major_material_info":["花生仁(生) 500克"],"seasoning_info":["花椒 2克","菜籽油 40克","五香粉 2克","精盐 10克"],"supplementary_material_info":[]},"nutrition_info":[{"热量(大卡)":"585.40"},{"碳水化合物(克)":"15.00"},{"脂肪(克)":"47.26"},{"蛋白质(克)":"22.41"},{"纤维素(克)":"5.09"}],"production_method":[" 1. 将洗净的花生米入沸水锅中煮1 分钟左右，迅速捞起，沥干水分；","2. 锅中下油，烧至五成热后，将花生米放入油锅中炸，炸时用漏勺不断地上下搅动，炸至花生米中水分已完全脱干，皮呈浅金黄色时，立即捞出，控油；","3. 趁花生米热时，撒上精盐、花椒粉和五香粉拌匀，密封于瓶中，随食随取。 "],"relative_foods_info":["油酥花生米"],"source":"薄荷","widget_unit_info":[]}
{"_id":"7D57Ob5P9i9vHQkd8lO9kvU4QnDeRv5Cl74mPcz2VhUrESzP","basic_info":{"calories_value":"20","cooking_type_detail":"干煸：此类菜肴烹调温度较高，蔬菜中的营养流失较大，同时相对比较油腻，减肥期间不宜多食。\n\n        ","food_group_name":"江西菜 ","food_name":"荷包青椒","traffic_light_img_href":"http://s2.boohee.cn/house/upload_food/2008/10/29/user_mid_151422_1225270731.jpg"},"href":"http://www.boohee.com/shiwu/hebaoqingjiao","material_info":{"major_material_info":["青椒 380克"],"seasoning_info":["大蒜 30克","酱油 30克","醋 15克","五香豆豉 15克","精盐 4克","味精 1克","花生油 20克"],"supplementary_material_info":[]},"nutrition_info":[{"热量(大卡)":"74.76"},{"碳水化合物(克)":"8.14"},{"脂肪(克)":"4.39"},{"蛋白质(克)":"2.56"},{"纤维素(克)":"1.87"}],"production_method":[" 1. 将青椒洗净，去蒂去籽，保持青椒完整不碎；","2. 大蒜去皮，用刀拍扁；","3. 将锅放旺火上烧红，放入青椒，用铁勺将青椒压扁，翻烧至青椒表皮呈现许多黑点时，将锅端离火口，停放30 秒钟；","4. 再置火上，倒入植物油，加大蒜、甜豆鼓、精盐、酱油、味精，拌炒20 秒钟，再放上醋即成。 "],"relative_foods_info":[],"source":"薄荷","widget_unit_info":[]}
{"_id":"G1LauCQOFG55WFxx0LmTWMzgMydeOfzMIzmMNPP7rxdAL37P","basic_info":{"calories_value":"30","cooking_type_detail":"焖：此类菜肴烹调时间较长，蔬菜的营养流失较为严重，但热量通常不高，减肥期间可以适量食用。\n\n        ","food_group_name":"江西菜 ","food_name":"栗子焖肉","traffic_light_img_href":"http://s2.boohee.cn/house/upload_food/2008/12/15/user_178969_1229320572.jpg"},"href":"http://www.boohee.com/shiwu/lizimenrou","material_info":{"major_material_info":["栗子(鲜) 500克","猪肉(肋条肉) 600克"],"seasoning_info":["味精 1克","小葱 15克","料酒 10克","精盐 4克","酱油 50克","猪油(炼) 50克"],"supplementary_material_info":[]},"nutrition_info":[{"热量(大卡)":"391.82"},{"碳水化合物(克)":"17.65"},{"脂肪(克)":"33.12"},{"蛋白质(克)":"6.53"},{"纤维素(克)":"0.72"}],"production_method":[" 1. 将栗子用沸水煮片刻，捞起，去壳去内皮，洗净晾干；","2. 五花肉切成2.4厘米见方的块；","3. 葱去根须，洗净，取葱白切段待用；","4. 炒锅置旺火上，加入熟猪油，烧至八成热时，倒入栗子迅速煸炒至熟，盛盆；","5. 原锅加入熟猪油少许烧热，将猪肉下锅煸至断生，下料酒、肉汤600毫升、精盐、酱油烧沸；","6. 烧沸后改用小火，放入栗子，焖至酥烂，待汤汁浓稠时，加味精、葱段，颠翻几下，盛入盘中。 "],"relative_foods_info":["栗子焖肉"],"source":"薄荷","widget_unit_info":[]}
{"_id":"Jr9c2TCqkDO5gBBUX2ckwta2RKOj1CfaQ3TFLqR9BrGDWB3N","basic_info":{"calories_value":"89","cooking_type_detail":"干煸：此类菜肴烹调温度较高，蔬菜中的营养流失较大，同时相对比较油腻，减肥期间不宜多食。\n\n        ","food_group_name":"江西菜 ","food_name":"炒血鸭","traffic_light_img_href":"http://s2.boohee.cn/house/upload_food/2016/9/14/mid_photo_url_4f1a6aa7aff44fdaa62a6c7080d2ae20.jpg"},"href":"http://www.boohee.com/shiwu/chaoxueya","material_info":{"major_material_info":["鸭 2000克"],"seasoning_info":["胡椒粉 1克","姜 6克","精盐 4克","辣椒(红，尖，干) 5克","味精 3克","小葱 15克","大蒜 25克","花生油 30克","香油 10克","料酒 35克","酱油 4克"],"supplementary_material_info":[]},"nutrition_info":[{"热量(大卡)":"244.25"},{"碳水化合物(克)":"0.79"},{"脂肪(克)":"20.33"},{"蛋白质(克)":"14.68"},{"纤维素(克)":"0.13"}],"production_method":[" 1. 取净碗一只，先装好料酒15 克，把鸭由颈下杀一刀，让鸭血流入碗内，用筷子搅匀；","2. 再将鸭子浸在沸水内烫一下，随即煺毛剖腹，挖出内脏，用刀切成1.8 厘米见方的块，另用碗装好待用（头、脚、翅、内脏等不用）；","3. 生姜洗净，切成1.2 厘米见方的薄片；","4. 葱去根须，洗净，取葱白切成1.2 厘米长小段；","5. 干红辣椒斜切成0.9 厘米长条；","6. 蒜瓣一切两半，一并放入净碗内；","7. 铁锅放旺火上烧热，倒入花生油，烧至七成热时，将切好的姜、葱、蒜、干红椒倒入炒出香味，再倒入鸭块合炒；","8. 炒至收缩变白，随即加料酒20克、酱油、精盐再炒；","9. 然后加鲜汤200毫升，将铁锅移微火上焖10 分钟；","10. 见汤约剩1/10 时将鸭血淋在鸭块上，边淋边炒动，使鸭块粘满鸭血，淋完后加胡椒粉、味精、略炒一下即起锅，盛入盘中，再淋上香油即成。 "],"relative_foods_info":["炒血鸭"],"source":"薄荷","widget_unit_info":[]}
{"_id":"PWY9HW6yow9OO6OK0vfh7yKCXo6QWBnqjA3exLgr09AEC0Gk","basic_info":{"calories_value":"129","cooking_type_detail":"卤：卤制菜肴通常不会额外添加大量油脂，因此菜肴大多热量适中，减肥期间可以适量食用。\n\n        ","food_group_name":"江西菜 ","food_name":"盐水牛腱","traffic_light_img_href":"http://s2.boohee.cn/house/upload_food/2016/10/28/mid_photo_url_a239b7ccd2334a9c838f78994ebeda9b.jpg"},"href":"http://www.boohee.com/shiwu/yanshuiniujian","material_info":{"major_material_info":["牛肉(后腱) 500克"],"seasoning_info":["料酒 10克","小葱 25克","姜 25克","肉桂 5克","味精 2克","精盐 15克","茴香 5克"],"supplementary_material_info":[]},"nutrition_info":[{"热量(大卡)":"90.11"},{"碳水化合物(克)":"2.73"},{"脂肪(克)":"0.92"},{"蛋白质(克)":"17.51"},{"纤维素(克)":"0.53"}],"production_method":[" 1. 将牛腱子肉洗净，去腱膜，放冷水中泡1 小时；","2. 浸泡后放开水锅中紧透，捞出，洗去血沫；","3. 葱姜洗净，葱切段，姜切块，均拍松；","4. 茴香籽、桂皮装小纱布袋内，系紧口，制成香料包；","5. 在锅内放清水烧开，加入葱姜、香料包、精盐、料酒、再放入牛腱子肉，烧开撇去浮沫；","6. 再转微火煨煮3 小时以上，至牛肉已烂；","7. 捞出牛肉，放盆中，从原汤中拣出葱、姜和料包，把汤倒入盛牛肉的盆内，晾凉；","8. 食用前将肉顶刀切成薄片，码入24 厘米盘中；","9. 上桌时，用鸡汤25毫升加入味精调匀，浇在牛肉上即成。 "],"relative_foods_info":["盐水牛腱","蒋记 盐水牛腱","蒋凤记 盐水牛腱"],"source":"薄荷","widget_unit_info":[]}
{"_id":"QNXrjNvSRkbH5PZbYiM64fVhfCZQn6eyHS5Wb1XrOqG5TkwK","basic_info":{"calories_value":"59","cooking_type_detail":"煎：食材煎后会吸收部分油脂导致热量提升，同时也易产生致癌物质，不利于健康，减肥期间应尽量少食煎制菜肴。\n\n        ","food_group_name":"江西菜 ","food_name":"南煎鸡排","traffic_light_img_href":"http://s2.boohee.cn/house/upload_food/2016/10/20/mid_photo_url_07dca692ef7f40caabcfa001e0d669fe.jpg"},"href":"http://www.boohee.com/shiwu/nanjianjipai","material_info":{"major_material_info":["童子鸡 1250克"],"seasoning_info":["料酒 3克","香油 10克","胡椒粉 1克","小葱 10克","精盐 2克","姜 8克","味精 2克","猪油(炼) 30克"],"supplementary_material_info":["香菜 5克","鸡蛋白(鸡蛋清) 75克","小麦面粉（特制） 100克"]},"nutrition_info":[{"热量(大卡)":"192.08"},{"碳水化合物(克)":"6.36"},{"脂肪(克)":"10.68"},{"蛋白质(克)":"17.68"},{"纤维素(克)":"0.03"}],"production_method":[" 1. 将子鸡宰杀，煺毛，去内脏洗净，取下翅边肉、腿肉四块，拆去骨，片成厚薄均匀的大片，然后剞上十字花刀（其余部分另作它用）；","2. 葱姜洗净，葱切葱花，姜切末；","3. 香菜择洗干净，切段；","4. 用精盐、料酒、味精、胡椒粉、葱花、姜未将鸡片腌10 分钟；","5. 鸡蛋清搅匀待用；","6. 将腌好的鸡片两面粘上面粉，逐块涂上蛋清；","7. 炒锅置中火上烧热，用熟猪油滑锅后，放适量油，将鸡片下锅煎至两面淡黄色，再用扦子插上若干小眼，淋上香油盛起；","8. 把煎好的鸡排，改刀成长4.5 厘米、宽1.5 厘米的条，装盘，周围摆上香菜，撒上椒盐即可。 "],"relative_foods_info":["南煎鸡排"],"source":"薄荷","widget_unit_info":[]}
{"_id":"UImJzZ1SBzSKIimepOyckcDhBkIEqSkQN2o7x90hCILElUMU","basic_info":{"calories_value":"29","cooking_type_detail":"凉拌：蔬菜类食材采取凉拌的烹调方式营养损失最小，是减肥期间推荐的烹调方式。\n\n        ","food_group_name":"江西菜 ","food_name":"凉拌粉丝","traffic_light_img_href":"http://s2.boohee.cn/house/food_mid/mid_photo_20128101113112921.jpg"},"href":"http://www.boohee.com/shiwu/liangbanfensi","material_info":{"major_material_info":["粉丝（干） 100克","饮用水 200克"],"seasoning_info":["每食富方便瓶美式芥末酱 5克","醋 5克","香油 10克","三得利 姜汁 2克","精盐 2克","大蒜 2克","味精 1克","小葱 2克","酱油 20克"],"supplementary_material_info":[]},"nutrition_info":[{"热量(大卡)":"129.28"},{"碳水化合物(克)":"25.18"},{"脂肪(克)":"2.99"},{"蛋白质(克)":"0.78"},{"纤维素(克)":"0.34"}],"production_method":[" 1.将粉丝用温水发软洗净，置沸水锅内煮3～5 分钟，然后捞入筲箕中，沥出水分，码上精盐拌匀后，盛入盘内。","2.将白酱油、辣椒油、香油、味精、芥末汁、姜汁、蒜泥、花椒油和醋调匀后淋入盛粉丝的盘中，再撒上香葱即成。","3.食之前，可入冰箱冷冻一下。 "],"relative_foods_info":["凉拌粉丝","57℃ 麻酱凉拌粉丝（原味）","57℃ 麻酱凉拌粉丝（酸辣味）"],"source":"薄荷","widget_unit_info":[{"1盘（小）凉拌粉丝(200.0克)":"259大卡"},{"标准(100克)":"129大卡"}]}
{"_id":"hdzEKhtG83tQu5f6dN9e6NAeo8Y4138UVRFK9OpYIB0CgXR9","basic_info":{"calories_value":"129","cooking_type_detail":"焖：此类菜肴烹调时间较长，蔬菜的营养流失较为严重，但热量通常不高，减肥期间可以适量食用。\n\n        ","food_group_name":"江西菜 ","food_name":"干烧猪脚","traffic_light_img_href":"http://s2.boohee.cn/house/food_mid/mid_photo_2012817853244195.jpg"},"href":"http://www.boohee.com/shiwu/ganshaozhujiao","material_info":{"major_material_info":["猪蹄 1000克"],"seasoning_info":["姜 15克","小葱 50克","八角 10克","酱油 100克","料酒 30克","冰糖 15克","味精 2克","饮用水 300克"],"supplementary_material_info":[]},"nutrition_info":[{"热量(大卡)":"181.73"},{"碳水化合物(克)":"2.43"},{"脂肪(克)":"12.41"},{"蛋白质(克)":"15.37"},{"纤维素(克)":"0.37"}],"production_method":[" 1.将猪脚（猪前蹄）洗净擦干水分，拔净猪毛；","2. 将拔净猪毛的猪脚用清水浸泡一下，再用小刀在水中刮净皮膜，取出擦干水分；","3. 然后将猪脚顺骨缝一分为二，改刀成块，用沸水焯一下，再放进冷水内洗净，捞起沥干水分备用；","4. 取大砂锅一只，锅底放入一块竹箅，以免在干烤时糊底，然后把猪脚放在竹箅上面，放入切好的姜片、葱段、八角，再依次放入清水、料酒、酱油、冰糖，把砂锅置于微火上焖；","5. 焖约3 小时，至汤汁近干时，放入适量味精再焖一下，焖至肉烂，汤平，猪脚全部呈金黄色，拣去葱、姜、茴香，即可上桌，也可把其放在盘中上桌。 "],"relative_foods_info":["干烧猪脚"],"source":"薄荷","widget_unit_info":[]}
{"_id":"hxZ1xzUo0pHKx56ibqotJ1erlGP2GZE7vumXGDqdbCUef7pz","basic_info":{"calories_value":"120","cooking_type_detail":"腌腊：此类菜肴往往钠盐过多，如果食材加工不善，可能存在不利于健康的亚硝酸盐，减肥期间应少食。\n\n        ","food_group_name":"江西菜 ","food_name":"腌毛蟹","traffic_light_img_href":"http://s2.boohee.cn/house/upload_food/2016/10/28/mid_photo_url_0fda5e10911440bdb4c27d94badc595b.jpg"},"href":"http://www.boohee.com/shiwu/amaoxie","material_info":{"major_material_info":["河蟹 500克"],"seasoning_info":["花椒 5克","冰糖 50克","精盐 60克","陈皮 10克","大葱 10克","汉口白酒(49.6度) 10克","姜 10克","黄酒 10克","大蒜 10克"],"supplementary_material_info":[]},"nutrition_info":[{"热量(大卡)":"120.00"},{"碳水化合物(克)":"11.38"},{"脂肪(克)":"2.03"},{"蛋白质(克)":"13.27"},{"纤维素(克)":"0.60"}],"production_method":[" 1.将活蟹放在500毫升的盐水盆中，10 分钟后捞出，再放入清水盆内，使其吐出腹中的水分和杂质；","2. 将蟹再用清水洗一遍，捞出，沥净水分后装入坛内，盖紧扣严；","3. 葱姜洗净，葱切成段，姜切片；","4. 冰糖碾碎；","5. 大蒜去蒜衣，拍松；","6. 锅内加水500毫升、精盐、花椒、冰糖屑、陈皮、葱、姜、蒜，煮沸几分钟，捞出葱、蒜，再倒入盆内晾凉；","7. 最后放入白酒和黄酒，随即倒入坛内，将蟹浸没，密封坛口，腌一周即可食用，随食随取。 "],"relative_foods_info":["腌毛蟹"],"source":"薄荷","widget_unit_info":[]}
{"_id":"hxhgtEeNgBQIcWFh7IOO8p5gStA8fVtRsbqmHahExI2mdXzX","basic_info":{"calories_value":"54","cooking_type_detail":"焦溜：焦溜最大的特点是一般要过两遍油，这样虽然口感更佳，但食材营养也更易被破坏，热量往往也更高，不利于健康与减肥。\n\n        ","food_group_name":"江西菜 ","food_name":"萁菜虾卷","traffic_light_img_href":"http://s2.boohee.cn/house/upload_food/2016/10/21/mid_photo_url_6de660f275ff453895eeb848da543044.jpg"},"href":"http://www.boohee.com/shiwu/jicaixiajuan","material_info":{"major_material_info":["虾仁（红） 150克","猪肉(肥) 100克"],"seasoning_info":["精盐 3克","味精 1克","小葱 10克","蚕豆淀粉 28克","香油 5克","猪油(炼) 15克"],"supplementary_material_info":["冬寒菜 60克","火腿 15克","鸡蛋白(鸡蛋清) 50克","香菇（鲜） 15克","饮用水 100克"]},"nutrition_info":[{"热量(大卡)":"228.88"},{"碳水化合物(克)":"5.18"},{"脂肪(克)":"20.66"},{"蛋白质(克)":"5.36"},{"纤维素(克)":"0.38"}],"production_method":[" 1. 将虾仁、肥肉洗净，分别剁成茸，各盛入碗内；","2. 取蛋清25克，加淀粉10 克，拌成蛋清糊；","3. 将蛋清糊和入虾茸内，同时加盐搅拌起劲；","4. 小葱去根须，洗净，取葱白切末；","5. 熟火腿切成末；","6. 香菇去蒂，洗净，切末；","7. 葱白末、火腿末、香菇末放进虾肉茸中，调成馅，分成30 份；","8. 萁菜叶（冬寒菜叶）洗净，用沸水烫片刻，捞起置清水中漂冷；","9. 在蛋清25克里加淀粉15克，调成蛋清浆；","10. 取一片萁菜叶摊开，涂上蛋清浆，放上虾肉馅一份，包成3.6 厘米长的小条，用蛋清糊封口，如此逐个包好；","11. 炒锅置旺火上烧热，加入熟猪油，烧至五六成热时，放入箕菜卷，待馅炸熟后，倒进漏勺沥油；","12. 原锅放鲜汤100毫升，用湿淀粉勾稀芡，倒萁菜卷，翻勺，挂汁，装盘，淋香油。 "],"relative_foods_info":["萁菜虾卷"],"source":"薄荷","widget_unit_info":[]}
{"_id":"kyMz6eluN8MXo0JbelW7JVhiigSnC0Iowc8fviuwOzTq7gX1","basic_info":{"calories_value":"99","cooking_type_detail":"清蒸：清蒸类菜肴往往清淡少油，食材营养流失也较少，是非常适宜减肥期间食用的菜肴类别。\n\n        ","food_group_name":"江西菜 ","food_name":"江西风味花椒鸡","traffic_light_img_href":"http://s2.boohee.cn/house/food_mid/mid_photo_2012817853244195.jpg"},"href":"http://www.boohee.com/shiwu/huajiaoji","material_info":{"major_material_info":["鸡 1000克"],"seasoning_info":["味精 2克","花椒 6克","醋 12克","酱油 15克","姜 5克","香油 15克","小葱 5克","精盐 5克"],"supplementary_material_info":[]},"nutrition_info":[{"热量(大卡)":"172.95"},{"碳水化合物(克)":"1.92"},{"脂肪(克)":"10.29"},{"蛋白质(克)":"18.35"},{"纤维素(克)":"0.18"}],"production_method":[" 1.将鸡宰杀治净，放入开水内煮约10 分钟至半熟，取出剁成长3.6 厘米，宽1.5 厘米的骨牌块；","2. 然后将鸡块一块靠一块地摆在碗中，鸡皮向下摆放整齐，最后摆上鸡头和碎鸡块；","3. 将香油倒入锅中，置旺火上烧热，投入花椒炸一下，至花椒呈现焦色，连油一起倒于鸡块碗内；","4. 另将味精、酱油、醋、精盐一起调匀，也倒入鸡块碗内；","5. 姜、葱洗净，均切成小段，放在鸡块上面；","6. 把鸡碗放入蒸笼，用旺火蒸约30 分钟，至鸡肉熟透，调味入骨，即出笼复扣在大盘上即成。 "],"relative_foods_info":["江西风味花椒鸡"],"source":"薄荷","widget_unit_info":[]}
{"_id":"o7xllGIbespRZw35amHzKAkQeu4zeBs9xUPAxEoiAs5kGmsE","basic_info":{"calories_value":"22","cooking_type_detail":"其他：\n\n        ","food_group_name":"江西菜 ","food_name":"糯米莲藕","traffic_light_img_href":"http://s2.boohee.cn/house/upload_food/2008/8/11/user_mid_105724_1218453544.jpg"},"href":"http://www.boohee.com/shiwu/nuomilianou","material_info":{"major_material_info":["藕 500克","糯米 100克","莲子(干) 75克","藕 500克"],"seasoning_info":["白砂糖 200克"],"supplementary_material_info":[]},"nutrition_info":[{"热量(大卡)":"155.82"},{"碳水化合物(克)":"34.72"},{"脂肪(克)":"0.33"},{"蛋白质(克)":"2.85"},{"纤维素(克)":"1.09"}],"production_method":[" 1. 将糯米淘洗干净，用清水浸泡30 分钟，捞起晾干水分；","2. 白莲（广昌白莲）洗净盛碗内，加上清水少许，入笼蒸20 分钟，取出透凉，削去蒂；","3. 将塘藕削去皮，用水洗净，先切去一端藕节，将糯米、白莲、灌入藕孔，藕孔填满后，用刀背轻轻地捶拍；","4. 再将装有糯米的藕放入沸水瓦钵内煮熟，取出晾凉，切片装盘，蘸食白糖，即可食用。 "],"relative_foods_info":["糯米莲藕"],"source":"薄荷","widget_unit_info":[]}
{"_id":"rlr6OzPlJ96Af7tXlXxt2CLijCH42X6aHYr1p3eZ9mwRJdKD","basic_info":{"calories_value":"93","cooking_type_detail":"熏、干：此类菜肴往往钠盐过多，如食材加工不善，可能存在不利于健康的亚硝酸盐，减肥期间应少食。\n\n        ","food_group_name":"江西菜 ","food_name":"庐山云雾熏石鸡","traffic_light_img_href":"http://s2.boohee.cn/house/upload_food/2016/10/19/mid_photo_url_cf0980e996a84261b3a0b77aff36374d.jpg"},"href":"http://www.boohee.com/shiwu/lushanyunwuxunshiji","material_info":{"major_material_info":["田鸡 500克"],"seasoning_info":["绿茶（茶叶本身） 15克","姜 15克","小葱 25克","花椒 5克","精盐 5克","酱油 5克","料酒 10克","味精 2克","白砂糖 10克","香油 15克"],"supplementary_material_info":["黄瓜 200克","粳米饭(蒸) 25克"]},"nutrition_info":[{"热量(大卡)":"93.39"},{"碳水化合物(克)":"4.45"},{"脂肪(克)":"2.69"},{"蛋白质(克)":"13.45"},{"纤维素(克)":"0.67"}],"production_method":[" 1. 将田鸡（石鸡）斩去头及爪尖，撕去皮，去内脏洗净；","2. 茶叶（云雾茶）盛小碗内，加适量开水浸泡成汁备用；","3. 葱洗净，切成末；","4. 将葱末5克、花椒加适量盐，入锅内，炒出香味，取出碾碎，做成葱椒盐，备用；","5. 将洗净的石鸡，放小盆内，以葱椒盐、酱油、料酒、味精、生姜、葱段、拌匀腌半小时；","6. 将黄瓜去蒂，洗净，切扇形用盐拌匀；","7. 取出铁锅一只，将大米饭、白糖、茶汁搅拌均匀，撒在锅底上，上面放一篦子，将葱叶放在篦子上；","8. 再将腌好的石鸡，双腿盘好放在葱叶上，加盖后开火；","9. 见开始有烟时改用微火，待烟由黑变白后，再从锅边淋入些茶汁，稍等片刻揭盖，熏制时间约15 分钟左右即可；","10. 装盘时，将鸡腿部朝外，围成圆形，把切好的黄瓜摆于盘中间，将每只石鸡都刷上一层麻油，并可跟碟调味。 "],"relative_foods_info":["庐山云雾熏石鸡"],"source":"薄荷","widget_unit_info":[]}
{"_id":"vbQv2JjECc9Wm8tV4CxGqXrhhBV6LIIJNZxlxOxTfp70b9qW","basic_info":{"calories_value":"129","cooking_type_detail":"卤：卤制菜肴通常不会额外添加大量油脂，因此菜肴大多热量适中，减肥期间可以适量食用。\n\n        ","food_group_name":"江西菜 ","food_name":"五香酱鸭","traffic_light_img_href":"http://s2.boohee.cn/house/menu_mid/1173676710994_mid.jpg"},"href":"http://www.boohee.com/shiwu/wuxiangjiangya","material_info":{"major_material_info":["鸭 1500克"],"seasoning_info":["姜 5克","甜面酱 5克","辣椒(红，尖，干) 5克","小葱 5克","肉桂 5克","酱油 25克","料酒 100克","花椒 2克","八角 5克","精盐 15克","香油 5克","陈皮 3克","茴香 2克","猪油(炼) 80克"],"supplementary_material_info":[]},"nutrition_info":[{"热量(大卡)":"252.43"},{"碳水化合物(克)":"0.79"},{"脂肪(克)":"21.65"},{"蛋白质(克)":"13.43"},{"纤维素(克)":"0.44"}],"production_method":[" 1. 鸭宰杀，煺毛，从尾脊背开口，掏出内脏洗净，斩去嘴巴、足爪，用精盐、酱油、料酒腌10 分钟；","2. 把八角、桂皮、陈皮、茴香籽、花椒等香料用干净纱布扎成香包；","3. 炒锅置旺火上烧热，舀入猪油烧呈七成熟时，将鸭子下锅炸至金黄色，捞起沥去油；","4. 原锅留油少许上火，把甜面酱入锅炒香，舀入适量清水，放进香包、姜块、葱白、红干椒、料酒和鸭子，用中火至入味，然后将鸭取出；","5. 取腰盘一只，将颈骨等垫底，然后把鸭斩成3.6 厘米长、1.8 厘米宽的块，排码成形，淋上香油即成。 "],"relative_foods_info":["五香酱鸭"],"source":"薄荷","widget_unit_info":[]}
{"_id":"vyZe7VZSRFNpbAC9OTtaRjkruNHXO4HaSNNEhVtRAys2iQGz","basic_info":{"calories_value":"55","cooking_type_detail":"糖溜、糖醋：加工过程中添加了糖和油脂，这二者都是减肥期间要少吃的，因此这类菜肴减肥时不宜食用。\n\n        ","food_group_name":"江西菜 ","food_name":"蛙式青鱼","traffic_light_img_href":"http://s2.boohee.cn/house/upload_food/2016/10/26/mid_photo_url_30814662718a41a8be3f7319479afd8a.jpg"},"href":"http://www.boohee.com/shiwu/washiqingyu","material_info":{"major_material_info":["青鱼 500克"],"seasoning_info":["精盐 7克","小葱 25克","料酒 15克","姜 20克","白砂糖 100克","辣椒(红，尖，干) 20克","白醋 25克","蚕豆淀粉 8克","小麦面粉（特制） 25克","胡椒粉 1克","花生油 7克"],"supplementary_material_info":["松花蛋(鸭蛋) 20克","蛋糕 20克","冬笋 100克","香菇（鲜） 20克"]},"nutrition_info":[{"热量(大卡)":"151.25"},{"碳水化合物(克)":"17.69"},{"脂肪(克)":"3.80"},{"蛋白质(克)":"12.79"},{"纤维素(克)":"1.19"}],"production_method":[" 1. 将青鱼刮鳞，去鳃，剖腹取出内脏，洗净；","2. 鸡蛋打入碗内，用竹筷子打成蛋液待用；","3. 用刀从鱼腹内片除脊骨，再片除胸刺，成头连接的两片鱼，然后用刀在两片鱼肉一面多剖十字花刀；","4. 冬笋去壳、老根，洗净，切成丝；","5. 香菇去蒂，洗净，切成细丝；","6. 生姜洗净，切成丝；","7. 红辣椒去蒂、籽，洗净，分别切成丝；","8. 葱去根须，洗净，切成2 厘米长的段待用；","9. 把细盐、料酒、胡椒粉均匀地抹在鱼内外，再粘上一层生粉拖上蛋液，再沾上一层干生粉，肉朝上装入漏勺内，再把鱼尾巴卷转，白蛋糕、皮蛋白做成蛙眼睛，制成蛙姿式；","10. 取锅置旺火上烧热，加入植物油，烧至八成熟，把漏勺放入，用炒勺不断把热油浇在鱼身上；","11. 定形后，入漏勺托炸，呈金黄色；","12. 同时另取锅上火，加底油，投入姜、葱、笋、红椒、冬菇、煸炒数下，加入清水，放入精盐、料酒、白糖，烧沸；","13. 待糖溶化，用湿淀粉勾芡，放入白醋，把鱼装盘，淋少许油，把糖醋汁浇在鱼上。 "],"relative_foods_info":["蛙式青鱼"],"source":"薄荷","widget_unit_info":[]}

{
  "_id": "vyZe7VZSRFNpbAC9OTtaRjkruNHXO4HaSNNEhVtRAys2iQGz",
  "basic_info": {
    "calories_value": "55",
    "cooking_type_detail": "糖溜、糖醋：加工过程中添加了糖和油脂，这二者都是减肥期间要少吃的，因此这类菜肴减肥时不宜食用。\n\n        ",
    "food_group_name": "江西菜 ",
    "food_name": "蛙式青鱼",
    "traffic_light_img_href": "http://s2.boohee.cn/house/upload_food/2016/10/26/mid_photo_url_30814662718a41a8be3f7319479afd8a.jpg"
  },
  "href": "http://www.boohee.com/shiwu/washiqingyu",
  "material_info": {
    "major_material_info": [
      "青鱼 500克"
    ],
    "seasoning_info": [
      "精盐 7克",
      "小葱 25克",
      "料酒 15克",
      "姜 20克",
      "白砂糖 100克",
      "辣椒(红，尖，干) 20克",
      "白醋 25克",
      "蚕豆淀粉 8克",
      "小麦面粉（特制） 25克",
      "胡椒粉 1克",
      "花生油 7克"
    ],
    "supplementary_material_info": [
      "松花蛋(鸭蛋) 20克",
      "蛋糕 20克",
      "冬笋 100克",
      "香菇（鲜） 20克"
    ]
  },
  "nutrition_info": [
    {
      "热量(大卡)": "151.25"
    },
    {
      "碳水化合物(克)": "17.69"
    },
    {
      "脂肪(克)": "3.80"
    },
    {
      "蛋白质(克)": "12.79"
    },
    {
      "纤维素(克)": "1.19"
    }
  ],
  "production_method": [
    " 1. 将青鱼刮鳞，去鳃，剖腹取出内脏，洗净；",
    "2. 鸡蛋打入碗内，用竹筷子打成蛋液待用；",
    "3. 用刀从鱼腹内片除脊骨，再片除胸刺，成头连接的两片鱼，然后用刀在两片鱼肉一面多剖十字花刀；",
    "4. 冬笋去壳、老根，洗净，切成丝；",
    "5. 香菇去蒂，洗净，切成细丝；",
    "6. 生姜洗净，切成丝；",
    "7. 红辣椒去蒂、籽，洗净，分别切成丝；",
    "8. 葱去根须，洗净，切成2 厘米长的段待用；",
    "9. 把细盐、料酒、胡椒粉均匀地抹在鱼内外，再粘上一层生粉拖上蛋液，再沾上一层干生粉，肉朝上装入漏勺内，再把鱼尾巴卷转，白蛋糕、皮蛋白做成蛙眼睛，制成蛙姿式；",
    "10. 取锅置旺火上烧热，加入植物油，烧至八成熟，把漏勺放入，用炒勺不断把热油浇在鱼身上；",
    "11. 定形后，入漏勺托炸，呈金黄色；",
    "12. 同时另取锅上火，加底油，投入姜、葱、笋、红椒、冬菇、煸炒数下，加入清水，放入精盐、料酒、白糖，烧沸；",
    "13. 待糖溶化，用湿淀粉勾芡，放入白醋，把鱼装盘，淋少许油，把糖醋汁浇在鱼上。 "
  ],
  "relative_foods_info": [
    "蛙式青鱼"
  ],
  "source": "薄荷",
  "widget_unit_info": []
}